[
    {
        "id": 1,
        "collection_id": "PRE1234",
        "student_name": "Nathan Humphries",
        "image": "avatar-11.jpg",
        "gender": "Male",
        "fees_type": "Exam Fees",
        "amount": "$278",
        "paid_date": "17 Nov 2020",
        "status": "Paid"
    },
    {
        "id": 2,
        "collection_id": "PRE1252",
        "student_name": "Joe Kelley",
        "image": "avatar-07.jpg",
        "gender": "Female",
        "fees_type": "Transport Fees",
        "amount": "$237",
        "paid_date": "17 Nov 2020",
        "status": "Paid"
    },
    {
        "id": 3,
        "collection_id": "PRE1434",
        "student_name": "Vincent",
        "image": "avatar-08.jpg",
        "gender": "Male",
        "fees_type": "Mess Fees",
        "amount": "$567",
        "paid_date": "05 Oct 2020",
        "status": "Paid"
    },
    {
        "id": 4,
        "collection_id": "PRE1534",
        "student_name": "Lois A",
        "image": "avatar-05.jpg",
        "gender": "Male",
        "fees_type": "Exam Fees",
        "amount": "$56",
        "paid_date": "02 Oct 2020",
        "status": "Unpaid"
    },
    {
        "id": 5,
        "collection_id": "PRE2143",
        "student_name": "Levell Scott",
        "image": "avatar-03.jpg",
        "gender": "Male",
        "fees_type": "Exam Fees",
        "amount": "$378",
        "paid_date": "04 Sep 2020",
        "status": "Paid"
    },
    {
        "id": 6,
        "collection_id": "PRE2153",
        "student_name": "Calvin",
        "image": "avatar-06.jpg",
        "gender": "Male",
        "fees_type": "Exam Fees",
        "amount": "$236",
        "paid_date": "28 Oct 2020",
        "status": "Unpaid"
    },
    {
        "id": 7,
        "collection_id": "PRE2209",
        "student_name": "Aaliyah",
        "image": "avatar-01.jpg",
        "gender": "Female",
        "fees_type": "Mess Fees",
        "amount": "$120",
        "paid_date": "17 Aug 2020",
        "status": "Paid"
    },
    {
        "id": 8,
        "collection_id": "PRE2213",
        "student_name": "Malynne",
        "image": "avatar-01.jpg",
        "gender": "Female",
        "fees_type": "Class Test",
        "amount": "$56",
        "paid_date": "05 Aug 2020",
        "status": "Paid"
    },
    {
        "id": 9,
        "collection_id": "PRE2345",
        "student_name": "Kozma  Tatari",
        "image": "avatar-09.jpg",
        "gender": "Female",
        "fees_type": "Exam Fees",
        "amount": "$564",
        "paid_date": "12 Nov 2020",
        "status": "Paid"
    },
    {
        "id": 10,
        "collection_id": "PRE2365",
        "student_name": "John Chambers",
        "image": "avatar-10.jpg",
        "gender": "Male",
        "fees_type": "Class Test",
        "amount": "$234",
        "paid_date": "15 Nov 2020",
        "status": "Paid"
    },
    {
        "id": 11,
        "collection_id": "PRE2431",
        "student_name": "Minnie",
        "image": "avatar-04.jpg",
        "gender": "Female",
        "fees_type": "Exam Fees",
        "amount": "$246",
        "paid_date": "17 Sep 2020",
        "status": "Unpaid"
    }
]